[
    {
        "subject": "안전관리론",
        "chapter_name": "1. 안전보건관리의 개요",
        "exam_year": 2023,
        "exam_round": 1,
        "question_text": "산업안전보건법령상 사업주의 의무로 틀린 것은?",
        "opt1": "국가의 산업재해 예방시책에 따를 것",
        "opt2": "근로자의 신체적 피로를 줄일 수 있는 작업환경을 조성할 것",
        "opt3": "안전 및 보건에 관하여 근로자에게 철저히 교육시킬 것",
        "opt4": "산업재해 발생 시 모든 책임을 근로자에게 전가할 것",
        "correct_answer": 4,
        "explanation": "사업주는 산업재해 예방 기준을 준수해야 하며, 사고 책임을 근로자에게 전가하는 것은 부당합니다."
    },
    {
        "subject": "안전관리론",
        "chapter_name": "2. 재해조사 및 분석",
        "exam_year": 2023,
        "exam_round": 2,
        "question_text": "무재해운동의 3원칙 중 '잠재위험을 사전에 발견, 파악, 해결하여 재해를 예방하는 것'을 의미하는 것은?",
        "opt1": "무(Zero)의 원칙",
        "opt2": "참가의 원칙",
        "opt3": "예방의 원칙",
        "opt4": "선취의 원칙",
        "correct_answer": 4,
        "explanation": "잠재위험 사전 발견 및 해결은 '선취의 원칙(안전제일의 원칙)'입니다."
    },
    {
        "subject": "안전관리론",
        "chapter_name": "3. 안전점검 및 검사",
        "exam_year": 2022,
        "exam_round": 1,
        "question_text": "안전점검의 종류 중 일정 기간마다 정기적으로 실시하는 점검은?",
        "opt1": "일상점검",
        "opt2": "수시점검",
        "opt3": "정기점검",
        "opt4": "임시점검",
        "correct_answer": 3,
        "explanation": "일정 주기(월, 분기, 반기 등)마다 정기적으로 하는 점검을 정기점검이라 합니다."
    },
    {
        "subject": "안전관리론",
        "chapter_name": "4. 보호구 및 안전표지",
        "exam_year": 2022,
        "exam_round": 3,
        "question_text": "안전모의 종류 중 내전압성이 가장 뛰어난 것은?",
        "opt1": "A형",
        "opt2": "AB형",
        "opt3": "AE형",
        "opt4": "ABE형",
        "correct_answer": 4,
        "explanation": "ABE형 안전모는 물체의 낙하, 비래, 추락 방지뿐 아니라 고압전기(내전압성)에 대한 보호 기능도 있습니다."
    },
    {
        "subject": "안전관리론",
        "chapter_name": "5. 산업안전심리",
        "exam_year": 2021,
        "exam_round": 2,
        "question_text": "매슬로우(Maslow)의 욕구단계설 중 가장 상위의 단계는?",
        "opt1": "생리적 욕구",
        "opt2": "안전의 욕구",
        "opt3": "자아실현의 욕구",
        "opt4": "사회적 욕구",
        "correct_answer": 3,
        "explanation": "매슬로우 욕구 5단계의 최상위는 '자아실현의 욕구'입니다."
    },
    {
        "subject": "안전관리론",
        "chapter_name": "6. 안전보건교육의 개념",
        "exam_year": 2020,
        "exam_round": 4,
        "question_text": "O.J.T (On the Job Training)의 특징으로 적절하지 않은 것은?",
        "opt1": "직장 내에서 업무와 병행하여 실시된다.",
        "opt2": "전문 강사를 초빙하여 집중적으로 교육하기 용이하다.",
        "opt3": "개별 지도가 가능하여 훈련 효과가 높다.",
        "opt4": "상사나 선배가 지도원이 된다.",
        "correct_answer": 2,
        "explanation": "전문 강사 초빙 등 외부 집합 교육은 Off J.T(Off the Job Training)의 특징입니다."
    },
    {
        "subject": "인간공학 및 시스템안전공학",
        "chapter_name": "1. 인간공학적 설계",
        "exam_year": 2023,
        "exam_round": 1,
        "question_text": "FTA(Fault Tree Analysis)에 사용되는 논리 기호 중, 입력 현상 중 어느 하나라도 발생하면 출력 현상이 발생하는 기호는?",
        "opt1": "AND 게이트",
        "opt2": "OR 게이트",
        "opt3": "억제 게이트",
        "opt4": "우선적 AND 게이트",
        "correct_answer": 2,
        "explanation": "입력 중 하나만 만족해도 출력이 발생하는 것은 논리합인 OR 게이트입니다."
    },
    {
        "subject": "인간공학 및 시스템안전공학",
        "chapter_name": "2. 정보입력 및 처리",
        "exam_year": 2022,
        "exam_round": 2,
        "question_text": "시각적 표시장치에서 눈금의 단위 등을 읽는 데 가장 큰 영향을 미치는 요인은?",
        "opt1": "조도와 대비",
        "opt2": "소음의 크기",
        "opt3": "공기의 온도",
        "opt4": "작업자의 체중",
        "correct_answer": 1,
        "explanation": "시각적 장치의 가독성에는 주변 조도와 배경 대비가 가장 큰 영향을 미칩니다."
    },
    {
        "subject": "인간공학 및 시스템안전공학",
        "chapter_name": "3. 부품배치의 원칙",
        "exam_year": 2021,
        "exam_round": 1,
        "question_text": "조종 장치나 표시 장치 배치 시 적용되는 원칙에 해당하지 않는 것은?",
        "opt1": "중요성의 원칙",
        "opt2": "사용 빈도의 원칙",
        "opt3": "심미성의 원칙",
        "opt4": "기능별 배치의 원칙",
        "correct_answer": 3,
        "explanation": "부품 배치 시에는 중요성, 사용 빈도, 기능별 배치, 사용 순서의 원칙 등이 우선되며 심미성(디자인적 아름다움)은 부차적인 요소입니다."
    },
    {
        "subject": "인간공학 및 시스템안전공학",
        "chapter_name": "4. 시스템 위험분석",
        "exam_year": 2023,
        "exam_round": 2,
        "question_text": "HAZOP 분석에서 사용하는 가이드 워드(Guide Word) 중 '설계 의도대로 완전히 이루어지지 않음'을 뜻하는 것은?",
        "opt1": "No, Not",
        "opt2": "More",
        "opt3": "Part of",
        "opt4": "As well as",
        "correct_answer": 3,
        "explanation": "Part of는 설계 의도의 일부만 달성되었음을 뜻하는 가이드 워드입니다."
    },
    {
        "subject": "인간공학 및 시스템안전공학",
        "chapter_name": "5. 인간 에러",
        "exam_year": 2022,
        "exam_round": 1,
        "question_text": "THERP(Technique for Human Error Rate Prediction) 기법의 주요 목적은?",
        "opt1": "기계 고장률 예측",
        "opt2": "인간 과오율 예측",
        "opt3": "시스템 복구 시간 분석",
        "opt4": "자연 재해 발생 빈도 예측",
        "correct_answer": 2,
        "explanation": "THERP은 인간이 수행하는 작업에서의 인적 오류(Human Error) 발생 확률을 예측하는 정량적 분석 기법입니다."
    },
    {
        "subject": "기계위험방지기술",
        "chapter_name": "1. 기계안전의 개념",
        "exam_year": 2023,
        "exam_round": 1,
        "question_text": "프레스 등의 금형을 부착/해체 시 슬라이드 불시 작동 방지를 위해 설치해야 하는 것은?",
        "opt1": "방호울",
        "opt2": "안전블록",
        "opt3": "광전자식 방호장치",
        "opt4": "양수조작식 방호장치",
        "correct_answer": 2,
        "explanation": "신체 일부가 들어가는 작업 시 불시 하강을 막는 물리적 지지 장치인 안전블록을 반드시 설치해야 합니다."
    },
    {
        "subject": "기계위험방지기술",
        "chapter_name": "2. 공작기계의 안전",
        "exam_year": 2022,
        "exam_round": 3,
        "question_text": "선반 작업 시 안전수칙으로 틀린 것은?",
        "opt1": "칩을 제거할 때는 반드시 브러시를 사용할 것",
        "opt2": "면장갑을 착용하고 작업할 것",
        "opt3": "바이트는 짧게 물리도록 할 것",
        "opt4": "가공물이 길 때는 심압대 등을 사용할 것",
        "correct_answer": 2,
        "explanation": "회전하는 기계(선반 등)를 취급할 때는 면장갑이 말려 들어갈 치명적 위험이 있어 결대 착용 금지입니다."
    },
    {
        "subject": "기계위험방지기술",
        "chapter_name": "3. 롤러기 및 원심기 안전",
        "exam_year": 2021,
        "exam_round": 2,
        "question_text": "롤러기의 급정지장치 중 복부조작식의 설치 높이 기준은?",
        "opt1": "0.4m 이상 ~ 0.6m 이내",
        "opt2": "0.8m 이상 ~ 1.1m 이내",
        "opt3": "1.2m 이상 ~ 1.5m 이내",
        "opt4": "1.8m 이상",
        "correct_answer": 2,
        "explanation": "복부조작식 롤러기 급정지장치의 설치 위치는 밑면에서 0.8m 이상 1.1m 이내입니다."
    },
    {
        "subject": "기계위험방지기술",
        "chapter_name": "4. 운반기계 안전",
        "exam_year": 2023,
        "exam_round": 2,
        "question_text": "지게차의 헤드가드(Head guard)의 설치 기준으로 적절하지 않은 것은?",
        "opt1": "강도는 최대하중의 2배 값의 등분포정하중에 견딜 것",
        "opt2": "상부틀의 각 개구의 폭은 16센티미터 미만일 것",
        "opt3": "운전자가 앉아서 조작하는 지게차의 바닥에서 상부틀 하면까지 1미터 이상일 것",
        "opt4": "입승식 지게차의 운전석 바닥면에서 상부틀 하면까지 1.5미터 이상일 것",
        "correct_answer": 4,
        "explanation": "입승식(서서 타는) 지게차 헤드가드의 바닥면에서 상부틀 하면까지의 거리는 1.88미터 이상이어야 합니다."
    },
    {
        "subject": "기계위험방지기술",
        "chapter_name": "5. 양중기 안전",
        "exam_year": 2020,
        "exam_round": 1,
        "question_text": "타워크레인의 운전작업 기준 중, 작업 중지를 명해야 하는 순간풍속 기준은?",
        "opt1": "초당 10m 초과",
        "opt2": "초당 15m 초과",
        "opt3": "초당 20m 초과",
        "opt4": "초당 30m 초과",
        "correct_answer": 2,
        "explanation": "순간풍속이 10m/s 초과 시 설치·수리 등 중지, 15m/s 초과 시 타워크레인 운전작업을 중지해야 합니다."
    },
    {
        "subject": "전기위험방지기술",
        "chapter_name": "1. 전격재해 및 방지대책",
        "exam_year": 2023,
        "exam_round": 1,
        "question_text": "누전차단기의 정격감도전류와 동작시간의 기준으로 가장 일반적인 것은?",
        "opt1": "30mA, 0.03초 이내",
        "opt2": "50mA, 0.05초 이내",
        "opt3": "100mA, 0.1초 이내",
        "opt4": "200mA, 0.2초 이내",
        "correct_answer": 1,
        "explanation": "산업안전보건기준에 따라 누전차단기는 감도전류 30mA 이하, 작동시간 0.03초 이내를 사용해야 합니다."
    },
    {
        "subject": "전기위험방지기술",
        "chapter_name": "2. 정전기 재해방지",
        "exam_year": 2022,
        "exam_round": 2,
        "question_text": "정전기 대전의 종류 중 액체류 등을 관내로 이송할 때 액체와 관 벽 간의 마찰로 발생하는 대전은?",
        "opt1": "마찰 대전",
        "opt2": "유동 대전",
        "opt3": "분출 대전",
        "opt4": "교반 대전",
        "correct_answer": 2,
        "explanation": "배관을 통해 액체가 흐를 때 내부 벽면과의 접촉 및 마찰로 인해 발생하는 정전기를 유동 대전이라 합니다."
    },
    {
        "subject": "전기위험방지기술",
        "chapter_name": "3. 전기설비의 방폭",
        "exam_year": 2021,
        "exam_round": 4,
        "question_text": "폭발성 가스나 증기가 정상 상태에서 연속적으로 장기간 체류하는 장소의 위험장소 등급은?",
        "opt1": "0종 장소",
        "opt2": "1종 장소",
        "opt3": "2종 장소",
        "opt4": "3종 장소",
        "correct_answer": 1,
        "explanation": "0종 장소는 위험 분위기가 지속적으로, 장기간 존재하는 구역을 의미합니다."
    },
    {
        "subject": "전기위험방지기술",
        "chapter_name": "4. 인체의 감전",
        "exam_year": 2023,
        "exam_round": 2,
        "question_text": "인체에 1mA 정도의 미세한 전류가 흐를 때 나타나는 생리적 현상은?",
        "opt1": "감지 전류",
        "opt2": "가사 상태",
        "opt3": "심실세동",
        "opt4": "마비 현상",
        "correct_answer": 1,
        "explanation": "1mA 정도의 교류 전류에서는 찌릿함을 느끼는 감지 전류 수준입니다."
    },
    {
        "subject": "전기위험방지기술",
        "chapter_name": "5. 접지설비",
        "exam_year": 2020,
        "exam_round": 1,
        "question_text": "전기기계기구의 금속제 외함에 접지를 하는 가장 주된 이유는?",
        "opt1": "기기의 수명 연장",
        "opt2": "누전 발생 시 감전사고 예방",
        "opt3": "전력 손실의 최소화",
        "opt4": "운전 속도 향상",
        "correct_answer": 2,
        "explanation": "금속에 접지를 하는 것은 누전 시 전압이 걸려도 인체로 흐르는 전류를 대지로 흘려보내 감전을 막기 위함입니다."
    },
    {
        "subject": "화학설비위험방지기술",
        "chapter_name": "1. 위험물 및 유해화학물질",
        "exam_year": 2023,
        "exam_round": 1,
        "question_text": "화학물질의 분류 기준 중 '인화성 액체'에 해당하는 것은?",
        "opt1": "인화점이 섭씨 90도 이하인 액체",
        "opt2": "인화점이 섭씨 60도 이하인 액체",
        "opt3": "인화점이 섭씨 100도 이상인 액체",
        "opt4": "인화점이 섭씨 20도 이하인 액체",
        "correct_answer": 2,
        "explanation": "관련 법규 상 인화점이 섭씨 60도 이하인 액체를 인화성 액체로 규정합니다."
    },
    {
        "subject": "화학설비위험방지기술",
        "chapter_name": "2. 공정안전관리(PSM)",
        "exam_year": 2022,
        "exam_round": 1,
        "question_text": "공정안전보고서(PSM) 제출 내용에 포함되지 않는 것은?",
        "opt1": "공정안전자료",
        "opt2": "공정위험성 평가서",
        "opt3": "안전운전계획",
        "opt4": "근로자 건강진단 결과서",
        "correct_answer": 4,
        "explanation": "공정안전보고서의 주요 내용은 공정안전자료, 위험성평가서, 안전운전/비상조치 계획이며 건강진단서는 미포함입니다."
    },
    {
        "subject": "화학설비위험방지기술",
        "chapter_name": "3. 화재 및 폭발 예방",
        "exam_year": 2021,
        "exam_round": 3,
        "question_text": "분진폭발을 일으킬 수 있는 물질이 아닌 것은?",
        "opt1": "밀가루",
        "opt2": "석탄가루",
        "opt3": "시멘트",
        "opt4": "마그네슘 분말",
        "correct_answer": 3,
        "explanation": "시멘트는 불연성 무기물이므로 산화반응에 의한 분진폭발을 일으키지 않습니다."
    },
    {
        "subject": "화학설비위험방지기술",
        "chapter_name": "4. 안전장치",
        "exam_year": 2023,
        "exam_round": 2,
        "question_text": "파열판(Rupture Disk)을 설치해야 하는 이유로 가장 적절한 것은?",
        "opt1": "급격한 압력상승 우려 시 순간적 배출",
        "opt2": "설비의 온도를 일정하게 유지",
        "opt3": "유체의 역류 역지",
        "opt4": "배관 내 슬러지 여과",
        "correct_answer": 1,
        "explanation": "파열판은 이상 반응 등으로 급격한 압력상승이 발생 시 즉시 파열되어 압력을 방출해 설비 파괴를 막습니다."
    },
    {
        "subject": "화학설비위험방지기술",
        "chapter_name": "5. 소화설비",
        "exam_year": 2020,
        "exam_round": 4,
        "question_text": "유류 화재(B급 화재)에 적합한 소화 방법으로 가장 거리가 먼 것은?",
        "opt1": "포말 소화기 사용",
        "opt2": "이산화탄소 소화기 사용",
        "opt3": "분말 소화기 사용",
        "opt4": "물에 의한 냉각 소화",
        "correct_answer": 4,
        "explanation": "유류에 물을 뿌리면 가벼운 기름이 물 위에 떠오르며 화재 면적이 급격히 확대됩니다."
    },
    {
        "subject": "건설안전기술",
        "chapter_name": "1. 건설공사 안전의 개요",
        "exam_year": 2023,
        "exam_round": 1,
        "question_text": "가설통로를 설치하는 경우 준수해야 할 기준으로 틀린 것은?",
        "opt1": "경사는 30도 이하로 할 것",
        "opt2": "경사가 15도를 초과하는 경우 미끄럼 방지 조치",
        "opt3": "추락 위험 시 안전난간 설치",
        "opt4": "수직갱 가설통로 길이 10m 이상 시 5m 이내마다 계단참 설치",
        "correct_answer": 4,
        "explanation": "수직갱 가설통로 길이가 15m 이상인 경우 10m 이내마다 계단참을 설치해야 하므로 4번 숫자가 틀렸습니다."
    },
    {
        "subject": "건설안전기술",
        "chapter_name": "2. 추락 및 낙하 재해방지",
        "exam_year": 2023,
        "exam_round": 2,
        "question_text": "안전대(Safety belt)의 종류 중 1개걸이 전용이 아닌 것은?",
        "opt1": "U자 걸이용",
        "opt2": "그네식",
        "opt3": "벨트식",
        "opt4": "로프식",
        "correct_answer": 1,
        "explanation": "U자 걸이는 전신주 작업 등에서 양쪽 리야드를 지지하여 작업 자세를 취하게 하는 것으로 1개걸이 전용이 아닙니다."
    },
    {
        "subject": "건설안전기술",
        "chapter_name": "3. 비계 및 가설구조물",
        "exam_year": 2022,
        "exam_round": 1,
        "question_text": "강관비계를 조립하는 경우 준수해야 할 사항으로 틀린 것은?",
        "opt1": "띠장 간격은 2.0m 이하로 할 것",
        "opt2": "비계기둥 간격은 띠장 방향으로 1.85m 이하로 할 것",
        "opt3": "비계기둥 간의 적재하중은 400kg을 초과하지 않도록 할 것",
        "opt4": "가장 윗부분에서 31m 떨어진 비계기둥은 1개의 강관으로 묶어 세울 것",
        "correct_answer": 4,
        "explanation": "비계기둥 윗부분으로부터 31m 떨어진 하단부는 2본의 강관으로 병립하여 세워야 합니다."
    },
    {
        "subject": "건설안전기술",
        "chapter_name": "4. 토목작업 안전",
        "exam_year": 2021,
        "exam_round": 2,
        "question_text": "굴착면의 안전 기울기 기준으로 흙이 습지인 경우 가장 올바른 기울기는?",
        "opt1": "1 : 0.5 이하",
        "opt2": "1 : 1 ~ 1 : 1.5",
        "opt3": "1 : 1.5 이상",
        "opt4": "1 : 0.3 이내",
        "correct_answer": 2,
        "explanation": "습지 상태 흙의 굴착면 기울기는 통상 1: 1 ~ 1: 1.5 비율을 유지해야 붕괴 위험을 줄일 수 있습니다."
    },
    {
        "subject": "건설안전기술",
        "chapter_name": "5. 해체 작업 안전",
        "exam_year": 2020,
        "exam_round": 3,
        "question_text": "구조물 해체작업 시 작성해야 하는 해체계획서에 포함될 사항으로 거리가 먼 것은?",
        "opt1": "해체의 방법 및 해체 순서도",
        "opt2": "소음 및 진동 방지 대책",
        "opt3": "해체작업용 기계 및 기구의 작업계획",
        "opt4": "해체 후 신축할 건축물의 조감도",
        "correct_answer": 4,
        "explanation": "해체계획서에는 공법, 안전대책, 분진 방지 대책이 들어가며, 신축 조감도는 불필요합니다."
    }
]